{
    "game_id": 2017020625,
    "year": 2018,
    "month": 1,
    "day": 5,
    "hour": 2,
    "reg_draw": 0,
    "home_team_id": 20,
    "home_team_name": "CGY",
    "home_goals": 4,
    "home_coach": "Glen Gulutzan",
    "away_team_id": 26,
    "away_team_name": "LAK",
    "away_goals": 3,
    "away_coach": "John Stevens",
    "players": {
        "home": {
            "8469608": 3594,
            "8470966": 1492,
            "8474673": 1452,
            "8474150": 1271,
            "8476346": 1212,
            "8470162": 673,
            "8479314": 1113,
            "8477508": 605,
            "8477903": 673,
            "8477497": 1186,
            "8474612": 1132,
            "8474628": 956,
            "8476462": 1199,
            "8471426": 926,
            "8476967": 688,
            "8476873": 783,
            "8475907": 1131,
            "8478233": 545,
            "8477935": 729
        },
        "away": {
            "8471734": 3473,
            "8474162": 1446,
            "8480147": 613,
            "8474563": 1837,
            "8477960": 768,
            "8471685": 1346,
            "8468483": 974,
            "8475160": 520,
            "8476404": 554,
            "8476406": 763,
            "8473453": 866,
            "8470606": 1195,
            "8475762": 1184,
            "8474166": 1430,
            "8469638": 512,
            "8477073": 696,
            "8476871": 1183,
            "8471338": 671,
            "8475726": 1089
        }
    }
}