{
    "game_id": 2017020966,
    "year": 2018,
    "month": 2,
    "day": 27,
    "hour": 0,
    "reg_draw": 1,
    "home_team_id": 14,
    "home_team_name": "TBL",
    "home_goals": 4,
    "home_coach": "Jon Cooper",
    "away_team_id": 10,
    "away_team_name": "TOR",
    "away_goals": 3,
    "away_coach": "Mike Babcock",
    "players": {
        "home": {
            "8476883": 3899,
            "8471958": 1093,
            "8471873": 1319,
            "8474870": 1185,
            "8476975": 619,
            "8470543": 1062,
            "8473986": 1404,
            "8478010": 1533,
            "8471339": 1083,
            "8476886": 469,
            "8476826": 1138,
            "8470601": 878,
            "8477205": 882,
            "8477454": 897,
            "8475167": 1691,
            "8476453": 319,
            "8476195": 570,
            "8474564": 1601,
            "8479410": 751
        },
        "away": {
            "8475883": 3900,
            "8468493": 1121,
            "8475786": 1024,
            "8466139": 1083,
            "8478483": 1066,
            "8469521": 698,
            "8479458": 1552,
            "8478408": 824,
            "8477953": 744,
            "8474037": 1075,
            "8477015": 944,
            "8477939": 898,
            "8476410": 681,
            "8475098": 1025,
            "8475172": 1056,
            "8476853": 1226,
            "8471392": 1133,
            "8473463": 896,
            "8474581": 1374
        }
    }
}