{
    "game_id": 2016020306,
    "year": 2016,
    "month": 11,
    "day": 25,
    "hour": 22,
    "reg_draw": 0,
    "home_team_id": 15,
    "home_team_name": "WSH",
    "home_goals": 3,
    "home_coach": "Barry Trotz",
    "away_team_id": 7,
    "away_team_name": "BUF",
    "away_goals": 1,
    "away_coach": "Dan Bylsma",
    "players": {
        "home": {
            "8475831": 3600,
            "8471702": 1389,
            "8471710": 741,
            "8471214": 924,
            "8475200": 1208,
            "8475792": 896,
            "8468508": 1014,
            "8473563": 1172,
            "8474189": 900,
            "8471476": 919,
            "8473991": 1184,
            "8476880": 751,
            "8468498": 1018,
            "8477444": 879,
            "8474590": 1380,
            "8477482": 397,
            "8474291": 794,
            "8475149": 1036,
            "8475744": 918
        },
        "away": {
            "8475195": 3497,
            "8470324": 1169,
            "8471742": 1226,
            "8475169": 1176,
            "8467407": 1109,
            "8471811": 548,
            "8473449": 1225,
            "8475728": 1202,
            "8477933": 992,
            "8470852": 800,
            "8474683": 629,
            "8476878": 547,
            "8476931": 1170,
            "8476166": 896,
            "8473992": 704,
            "8477478": 494,
            "8477499": 1646,
            "8475220": 752,
            "8475158": 1433
        }
    }
}