{
    "game_id": 2016020617,
    "year": 2017,
    "month": 1,
    "day": 11,
    "hour": 1,
    "reg_draw": 1,
    "home_team_id": 16,
    "home_team_name": "CHI",
    "home_goals": 4,
    "home_coach": "Joel Quenneville",
    "away_team_id": 17,
    "away_team_name": "DET",
    "away_goals": 3,
    "away_coach": "Jeff Blashill",
    "players": {
        "home": {
            "8470645": 3614,
            "8470281": 1635,
            "8471769": 1324,
            "8479482": 788,
            "8470607": 1289,
            "8471956": 372,
            "8475209": 770,
            "8473573": 1357,
            "8473604": 1263,
            "8469547": 355,
            "8477451": 663,
            "8476994": 911,
            "8466285": 1020,
            "8477845": 1182,
            "8478528": 652,
            "8477929": 459,
            "8478550": 1332,
            "8466148": 1148,
            "8474141": 1416
        },
        "away": {
            "8475852": 3638,
            "8471716": 521,
            "8474679": 917,
            "8475772": 820,
            "8470778": 848,
            "8475193": 547,
            "8471242": 1447,
            "8477511": 1095,
            "8468083": 1158,
            "8476822": 879,
            "8476450": 478,
            "8470144": 909,
            "8470318": 1332,
            "8476289": 1350,
            "8476443": 1205,
            "8470598": 826,
            "8477215": 1457,
            "8477946": 691,
            "8476960": 905
        }
    }
}