{
    "game_id": 2016020938,
    "year": 2017,
    "month": 3,
    "day": 3,
    "hour": 0,
    "reg_draw": 1,
    "home": {
        "team_id": 4,
        "team": "PHI",
        "coach": "Dave Hakstol",
        "GF": 1,
        "GF-5on5": 1,
        "GF-PP": 0,
        "GF-SH": 0,
        "SF": 49,
        "SF-5on5": 43,
        "SF-PP": 6,
        "SF-SH": 0,
        "PIM": 8,
        "PP-O": 4,
        "BLK": 12,
        "TAW": 12,
        "GAW": 16,
        "FO-T": 59,
        "FO-W": 28,
        "HIT": 29
    },
    "away": {
        "team_id": 13,
        "team": "FLA",
        "coach": "Tom Rowe",
        "GF": 1,
        "GF-5on5": 0,
        "GF-PP": 0,
        "GF-SH": 1,
        "SF": 40,
        "SF-5on5": 32,
        "SF-PP": 6,
        "SF-SH": 2,
        "PIM": 12,
        "PP-O": 2,
        "BLK": 15,
        "TAW": 7,
        "GAW": 11,
        "FO-T": 59,
        "FO-W": 31,
        "HIT": 27
    }
}