{
    "game_id": 2018021010,
    "year": 2019,
    "month": 3,
    "day": 3,
    "hour": 20,
    "reg_draw": 0,
    "home": {
        "team_id": 2,
        "team": "NYI",
        "coach": "Barry Trotz",
        "GF": 1,
        "GF-5on5": 1,
        "GF-PP": 0,
        "GF-SH": 0,
        "SF": 30,
        "SF-5on5": 28,
        "SF-PP": 2,
        "SF-SH": 0,
        "PIM": 7,
        "PP-O": 2,
        "BLK": 12,
        "TAW": 5,
        "GAW": 16,
        "FO-T": 64,
        "FO-W": 29,
        "HIT": 29
    },
    "away": {
        "team_id": 4,
        "team": "PHI",
        "coach": "Scott Gordon",
        "GF": 4,
        "GF-5on5": 4,
        "GF-PP": 0,
        "GF-SH": 0,
        "SF": 26,
        "SF-5on5": 24,
        "SF-PP": 2,
        "SF-SH": 0,
        "PIM": 9,
        "PP-O": 1,
        "BLK": 19,
        "TAW": 7,
        "GAW": 12,
        "FO-T": 64,
        "FO-W": 35,
        "HIT": 21
    }
}