{
    "game_id": 2013020899,
    "year": 2014,
    "month": 3,
    "day": 1,
    "hour": 2,
    "reg_draw": 0,
    "home_team_id": 21,
    "home_team_name": "COL",
    "home_goals": 4,
    "home_coach": "Patrick Roy",
    "away_team_id": 27,
    "away_team_name": "PHX",
    "away_goals": 2,
    "away_coach": "Dave Tippett",
    "players": {
        "home": {
            "8473575": 3600,
            "8474207": 1215,
            "8475197": 1012,
            "8470317": 1088,
            "8470750": 1001,
            "8470699": 1254,
            "8475168": 1032,
            "8473465": 983,
            "8469707": 964,
            "8464981": 1156,
            "8471718": 581,
            "8470171": 956,
            "8471669": 947,
            "8477492": 1000,
            "8471657": 585,
            "8471326": 343,
            "8470378": 1285,
            "8475158": 1067,
            "8476455": 998
        },
        "away": {
            "8471306": 3491,
            "8471735": 1552,
            "8469760": 1152,
            "8473673": 854,
            "8471691": 1005,
            "8467831": 767,
            "8468085": 1126,
            "8469664": 837,
            "8462038": 1207,
            "8475171": 1665,
            "8471231": 677,
            "8474628": 900,
            "8471232": 850,
            "8473970": 731,
            "8474646": 634,
            "8468535": 1167,
            "8464966": 1082,
            "8467371": 541,
            "8474571": 1014
        }
    }
}