{
    "game_id": 2015020339,
    "year": 2015,
    "month": 11,
    "day": 28,
    "hour": 0,
    "reg_draw": 1,
    "home_team_id": 13,
    "home_goals": 3,
    "home_coach": "Gerard Gallant",
    "away_team_id": 2,
    "away_goals": 2,
    "away_coach": "Jack Capuano",
    "players": {
        "home": {
            "8466141": 3900,
            "8474000": 1350,
            "8477932": 1371,
            "8475755": 1098,
            "8476456": 1266,
            "8477493": 1162,
            "8468001": 797,
            "8475191": 1307,
            "8476389": 889,
            "8475760": 1156,
            "8465185": 1166,
            "8469638": 884,
            "8475769": 660,
            "8475790": 1251,
            "8476400": 807,
            "8466285": 1327,
            "8448208": 807,
            "8475204": 975,
            "8475736": 694
        },
        "away": {
            "8470860": 3900,
            "8475181": 1509,
            "8474612": 1533,
            "8474573": 962,
            "8473504": 712,
            "8474709": 717,
            "8476458": 797,
            "8473449": 1169,
            "8475314": 952,
            "8469623": 781,
            "8475754": 1189,
            "8473565": 822,
            "8475177": 1481,
            "8470144": 1117,
            "8475231": 715,
            "8470187": 1550,
            "8471362": 849,
            "8473579": 819,
            "8475166": 1346
        }
    },
    "home_team": "FLA",
    "away_team": "NYI"
}