{
    "game_id": 2015020991,
    "year": 2016,
    "month": 3,
    "day": 8,
    "hour": 3,
    "reg_draw": 1,
    "home_team_id": 24,
    "home_goals": 1,
    "home_coach": "Bruce Boudreau",
    "away_team_id": 15,
    "away_goals": 2,
    "away_coach": "Barry Trotz",
    "players": {
        "home": {
            "8476434": 3889,
            "8469598": 1411,
            "8475764": 1433,
            "8471699": 985,
            "8470621": 1058,
            "8470612": 1272,
            "8476116": 615,
            "8470616": 1428,
            "8475155": 1209,
            "8471390": 448,
            "8475164": 1122,
            "8477941": 593,
            "8476312": 971,
            "8470775": 729,
            "8475222": 1357,
            "8476854": 1151,
            "8474102": 948,
            "8476483": 984,
            "8473465": 839
        },
        "away": {
            "8474651": 3900,
            "8471702": 1625,
            "8473426": 911,
            "8471214": 1229,
            "8475200": 1177,
            "8470617": 898,
            "8468508": 977,
            "8473563": 1004,
            "8466251": 806,
            "8471476": 971,
            "8473991": 1294,
            "8476880": 686,
            "8468498": 1314,
            "8477444": 762,
            "8471698": 946,
            "8474291": 1005,
            "8477220": 869,
            "8475149": 970,
            "8475744": 1112
        }
    },
    "home_team": "ANA",
    "away_team": "WSH"
}