{
    "game_id": 2019020919,
    "year": 2020,
    "month": 2,
    "day": 18,
    "hour": 2,
    "reg_draw": 1,
    "home_team_id": 21,
    "home_goals": 3,
    "home_coach": "Jared Bednar",
    "away_team_id": 14,
    "away_goals": 4,
    "away_coach": "Jon Cooper",
    "players": {
        "home": {
            "8480925": 3783,
            "8473446": 1060,
            "8480069": 1556,
            "8477501": 1016,
            "8477507": 723,
            "8479370": 763,
            "8477435": 1162,
            "8474013": 1173,
            "8477492": 1633,
            "8476391": 440,
            "8477456": 1033,
            "8477930": 689,
            "8479398": 1253,
            "8475820": 1049,
            "8477973": 662,
            "8476442": 796,
            "8476455": 1456,
            "8477444": 1468,
            "8478420": 497
        },
        "away": {
            "8470147": 3783,
            "8474568": 791,
            "8474870": 828,
            "8476975": 896,
            "8474034": 743,
            "8473986": 1076,
            "8476292": 904,
            "8478010": 1187,
            "8474031": 1180,
            "8477409": 412,
            "8474611": 731,
            "8476826": 676,
            "8478477": 487,
            "8478519": 1172,
            "8475167": 1791,
            "8478416": 1297,
            "8476453": 1192,
            "8474564": 1252,
            "8479410": 1493
        }
    },
    "home_team": "COL",
    "away_team": "TBL"
}