{
    "game_id": 2019020233,
    "year": 2019,
    "month": 11,
    "day": 6,
    "hour": 3,
    "reg_draw": 0,
    "home_team_id": 24,
    "home_team_name": "ANA",
    "home_goals": 2,
    "home_coach": "Dallas Eakins",
    "away_team_id": 30,
    "away_team_name": "MIN",
    "away_goals": 4,
    "away_coach": "Bruce Boudreau",
    "players": {
        "home": {
            "8476434": 3512,
            "8475764": 1388,
            "8473560": 924,
            "8475790": 1237,
            "8474641": 1028,
            "8470612": 1237,
            "8477240": 636,
            "8478131": 1046,
            "8478491": 873,
            "8475164": 1140,
            "8479351": 845,
            "8477941": 1028,
            "8474683": 677,
            "8474584": 1251,
            "8476854": 1309,
            "8479368": 581,
            "8480031": 929,
            "8478873": 748,
            "8476483": 971
        },
        "away": {
            "8471774": 3600,
            "8477987": 559,
            "8469459": 1053,
            "8470610": 932,
            "8470595": 904,
            "8478493": 989,
            "8475722": 1012,
            "8475220": 1024,
            "8478413": 846,
            "8479316": 991,
            "8470600": 1555,
            "8477369": 705,
            "8477942": 673,
            "8476856": 1288,
            "8476463": 1276,
            "8475692": 929,
            "8477451": 648,
            "8474716": 1520,
            "8476779": 856
        }
    }
}