{
    "game_id": 2015020938,
    "year": 2016,
    "month": 3,
    "day": 1,
    "hour": 0,
    "reg_draw": 0,
    "home": {
        "team_id": 4,
        "team": "PHI",
        "coach": "Dave Hakstol",
        "GF": 5,
        "GF-5on5": 2,
        "GF-PP": 2,
        "GF-SH": 0,
        "SF": 29,
        "SF-5on5": 21,
        "SF-PP": 5,
        "SF-SH": 2,
        "PIM": 10,
        "PP-O": 3,
        "BLK": 21,
        "TAW": 7,
        "GAW": 17,
        "FO-T": 57,
        "FO-W": 29,
        "HIT": 20
    },
    "away": {
        "team_id": 20,
        "team": "CGY",
        "coach": "Bob Hartley",
        "GF": 3,
        "GF-5on5": 2,
        "GF-PP": 1,
        "GF-SH": 0,
        "SF": 32,
        "SF-5on5": 26,
        "SF-PP": 6,
        "SF-SH": 0,
        "PIM": 8,
        "PP-O": 4,
        "BLK": 23,
        "TAW": 8,
        "GAW": 11,
        "FO-T": 57,
        "FO-W": 28,
        "HIT": 34
    }
}