{
    "game_id": 2019020649,
    "year": 2020,
    "month": 1,
    "day": 5,
    "hour": 0,
    "reg_draw": 0,
    "home_team_id": 1,
    "home_team": "NJD",
    "home_goals": 2,
    "home_coach": "Alain Nasreddine",
    "away_team_id": 21,
    "away_team": "COL",
    "away_goals": 5,
    "away_coach": "Jared Bednar",
    "players": {
        "home": {
            "8478406": {
                "icetime": 3448,
                "position": "G"
            },
            "8472382": {
                "icetime": 1040,
                "position": "D"
            },
            "8477355": {
                "icetime": 887,
                "position": "D"
            },
            "8480002": {
                "icetime": 1311,
                "position": "C"
            },
            "8477401": {
                "icetime": 624,
                "position": "C"
            },
            "8479291": {
                "icetime": 608,
                "position": "C"
            },
            "8474190": {
                "icetime": 617,
                "position": "R"
            },
            "8471233": {
                "icetime": 1029,
                "position": "C"
            },
            "8476399": {
                "icetime": 1069,
                "position": "C"
            },
            "8475151": {
                "icetime": 1183,
                "position": "R"
            },
            "8477509": {
                "icetime": 826,
                "position": "D"
            },
            "8476923": {
                "icetime": 1596,
                "position": "D"
            },
            "8476043": {
                "icetime": 592,
                "position": "C"
            },
            "8478401": {
                "icetime": 1201,
                "position": "C"
            },
            "8477425": {
                "icetime": 754,
                "position": "L"
            },
            "8475222": {
                "icetime": 1840,
                "position": "D"
            },
            "8474056": {
                "icetime": 1031,
                "position": "D"
            },
            "8480003": {
                "icetime": 565,
                "position": "C"
            },
            "8477038": {
                "icetime": 1019,
                "position": "L"
            }
        },
        "away": {
            "8475831": {
                "icetime": 3600,
                "position": "G"
            },
            "8473446": {
                "icetime": 1189,
                "position": "D"
            },
            "8480069": {
                "icetime": 1242,
                "position": "D"
            },
            "8474685": {
                "icetime": 881,
                "position": "L"
            },
            "8477507": {
                "icetime": 923,
                "position": "D"
            },
            "8479370": {
                "icetime": 567,
                "position": "C"
            },
            "8477435": {
                "icetime": 1083,
                "position": "D"
            },
            "8474013": {
                "icetime": 1233,
                "position": "D"
            },
            "8477492": {
                "icetime": 1229,
                "position": "C"
            },
            "8477456": {
                "icetime": 983,
                "position": "L"
            },
            "8477930": {
                "icetime": 804,
                "position": "C"
            },
            "8479398": {
                "icetime": 1223,
                "position": "D"
            },
            "8475820": {
                "icetime": 1134,
                "position": "R"
            },
            "8477973": {
                "icetime": 577,
                "position": "C"
            },
            "8476442": {
                "icetime": 911,
                "position": "L"
            },
            "8475172": {
                "icetime": 862,
                "position": "C"
            },
            "8476455": {
                "icetime": 1089,
                "position": "L"
            },
            "8477444": {
                "icetime": 797,
                "position": "L"
            },
            "8478420": {
                "icetime": 898,
                "position": "R"
            }
        }
    }
}