{
    "game_id": 2013020624,
    "year": 2014,
    "month": 1,
    "day": 4,
    "hour": 2,
    "reg_draw": 0,
    "home": {
        "team_id": 20,
        "team": "CGY",
        "coach": "Bob Hartley",
        "GF": 0,
        "GF-5on5": 0,
        "GF-PP": 0,
        "GF-SH": 0,
        "SF": 19,
        "SF-5on5": 15,
        "SF-PP": 4,
        "SF-SH": 0,
        "PIM": 17,
        "PP-O": 5,
        "BLK": 13,
        "TAW": 8,
        "GAW": 15,
        "FO-T": 49,
        "FO-W": 26,
        "HIT": 17
    },
    "away": {
        "team_id": 14,
        "team": "TBL",
        "coach": "Jon Cooper",
        "GF": 2,
        "GF-5on5": 2,
        "GF-PP": 0,
        "GF-SH": 0,
        "SF": 29,
        "SF-5on5": 19,
        "SF-PP": 8,
        "SF-SH": 2,
        "PIM": 17,
        "PP-O": 5,
        "BLK": 21,
        "TAW": 7,
        "GAW": 15,
        "FO-T": 49,
        "FO-W": 23,
        "HIT": 9
    }
}