{
    "game_id": 2014020161,
    "year": 2014,
    "month": 11,
    "day": 2,
    "hour": 0,
    "reg_draw": 1,
    "home": {
        "team_id": 19,
        "team": "STL",
        "coach": "Ken Hitchcock",
        "GF": 2,
        "GF-5on5": 2,
        "GF-PP": 0,
        "GF-SH": 0,
        "SF": 29,
        "SF-5on5": 22,
        "SF-PP": 7,
        "SF-SH": 0,
        "PIM": 8,
        "PP-O": 3,
        "BLK": 11,
        "TAW": 5,
        "GAW": 4,
        "FO-T": 68,
        "FO-W": 42,
        "HIT": 17
    },
    "away": {
        "team_id": 21,
        "team": "COL",
        "coach": "Patrick Roy",
        "GF": 2,
        "GF-5on5": 0,
        "GF-PP": 2,
        "GF-SH": 0,
        "SF": 29,
        "SF-5on5": 16,
        "SF-PP": 13,
        "SF-SH": 0,
        "PIM": 6,
        "PP-O": 4,
        "BLK": 16,
        "TAW": 5,
        "GAW": 3,
        "FO-T": 68,
        "FO-W": 26,
        "HIT": 23
    }
}