{
    "game_id": 2014020332,
    "year": 2014,
    "month": 11,
    "day": 28,
    "hour": 1,
    "reg_draw": 1,
    "home": {
        "team_id": 18,
        "team": "NSH",
        "coach": "Peter Laviolette",
        "GF": 1,
        "GF-5on5": 1,
        "GF-PP": 0,
        "GF-SH": 0,
        "SF": 25,
        "SF-5on5": 18,
        "SF-PP": 7,
        "SF-SH": 0,
        "PIM": 10,
        "PP-O": 5,
        "BLK": 14,
        "TAW": 6,
        "GAW": 14,
        "FO-T": 61,
        "FO-W": 28,
        "HIT": 17
    },
    "away": {
        "team_id": 22,
        "team": "EDM",
        "coach": "Dallas Eakins",
        "GF": 0,
        "GF-5on5": 0,
        "GF-PP": 0,
        "GF-SH": 0,
        "SF": 37,
        "SF-5on5": 30,
        "SF-PP": 4,
        "SF-SH": 3,
        "PIM": 22,
        "PP-O": 4,
        "BLK": 17,
        "TAW": 7,
        "GAW": 2,
        "FO-T": 61,
        "FO-W": 33,
        "HIT": 12
    }
}