{
    "game_id": 2014020744,
    "year": 2015,
    "month": 2,
    "day": 3,
    "hour": 3,
    "reg_draw": 1,
    "home": {
        "team_id": 28,
        "team": "SJS",
        "coach": "Todd McLellan",
        "GF": 4,
        "GF-5on5": 3,
        "GF-PP": 1,
        "GF-SH": 0,
        "SF": 37,
        "SF-5on5": 35,
        "SF-PP": 1,
        "SF-SH": 1,
        "PIM": 2,
        "PP-O": 2,
        "BLK": 16,
        "TAW": 12,
        "GAW": 19,
        "FO-T": 68,
        "FO-W": 35,
        "HIT": 34
    },
    "away": {
        "team_id": 22,
        "team": "EDM",
        "coach": "Todd Nelson",
        "GF": 4,
        "GF-5on5": 4,
        "GF-PP": 0,
        "GF-SH": 0,
        "SF": 40,
        "SF-5on5": 36,
        "SF-PP": 4,
        "SF-SH": 0,
        "PIM": 4,
        "PP-O": 1,
        "BLK": 14,
        "TAW": 11,
        "GAW": 16,
        "FO-T": 68,
        "FO-W": 33,
        "HIT": 26
    }
}