{
    "game_id": 2015021105,
    "year": 2016,
    "month": 3,
    "day": 24,
    "hour": 23,
    "reg_draw": 0,
    "home_team_id": 17,
    "home_team_name": "DET",
    "home_goals": 4,
    "home_coach": "Jeff Blashill",
    "away_team_id": 8,
    "away_team_name": "MTL",
    "away_goals": 3,
    "away_coach": "Michel Therrien",
    "players": {
        "home": {
            "8475852": 3569,
            "8474090": 1099,
            "8471716": 1233,
            "8467514": 1149,
            "8474679": 871,
            "8475772": 901,
            "8467389": 737,
            "8475193": 757,
            "8471242": 1188,
            "8470724": 1316,
            "8477511": 722,
            "8468083": 1222,
            "8476822": 851,
            "8471794": 975,
            "8470318": 820,
            "8468509": 1117,
            "8477215": 1223,
            "8477946": 1089,
            "8476960": 504
        },
        "away": {
            "8475681": 3535,
            "8474688": 1179,
            "8471371": 533,
            "8469521": 1165,
            "8471338": 1074,
            "8476870": 627,
            "8476479": 708,
            "8476851": 1003,
            "8476470": 1124,
            "8477446": 693,
            "8474038": 968,
            "8476379": 821,
            "8471976": 950,
            "8476451": 438,
            "8474157": 1060,
            "8477810": 871,
            "8471296": 1593,
            "8467496": 1612,
            "8474189": 976
        }
    }
}