{
    "game_id": 2018020870,
    "year": 2019,
    "month": 2,
    "day": 13,
    "hour": 1,
    "reg_draw": 0,
    "home_team_id": 18,
    "home_goals": 2,
    "home_coach": "Peter Laviolette",
    "away_team_id": 17,
    "away_goals": 3,
    "away_coach": "Jeff Blashill",
    "players": {
        "home": {
            "8471469": 3531,
            "8475176": 1306,
            "8469465": 577,
            "8474134": 472,
            "8474068": 923,
            "8476887": 1229,
            "8476925": 695,
            "8470619": 752,
            "8474009": 984,
            "8475218": 1359,
            "8475225": 898,
            "8475714": 766,
            "8477942": 876,
            "8476428": 590,
            "8478042": 1164,
            "8477451": 615,
            "8474600": 1594,
            "8474056": 1649,
            "8475793": 1214
        },
        "away": {
            "8470657": 3591,
            "8475324": 1110,
            "8471716": 860,
            "8474679": 1172,
            "8471242": 1029,
            "8470598": 666,
            "8479992": 477,
            "8477511": 1107,
            "8476822": 944,
            "8471794": 816,
            "8470144": 780,
            "8470318": 1265,
            "8468509": 1171,
            "8477455": 649,
            "8477215": 1295,
            "8478036": 647,
            "8477946": 1279,
            "8476960": 855,
            "8470110": 1166
        }
    },
    "home_team": "NSH",
    "away_team": "DET"
}