{
    "game_id": 2016020642,
    "year": 2017,
    "month": 1,
    "day": 15,
    "hour": 0,
    "reg_draw": 0,
    "home_team_id": 8,
    "home_goals": 5,
    "home_coach": "Michel Therrien",
    "away_team_id": 3,
    "away_goals": 4,
    "away_coach": "Alain Vigneault",
    "players": {
        "home": {
            "8471679": 3600,
            "8470642": 1529,
            "8469521": 1104,
            "8471338": 660,
            "8474743": 649,
            "8476479": 1074,
            "8473507": 1353,
            "8476851": 997,
            "8476470": 1500,
            "8476808": 768,
            "8477446": 438,
            "8474038": 1202,
            "8477413": 656,
            "8474717": 631,
            "8471228": 1125,
            "8477476": 864,
            "8476381": 319,
            "8474157": 1286,
            "8471296": 1421
        },
        "away": {
            "8468685": 2314,
            "8477293": 1200,
            "8476431": 1159,
            "8471958": 1103,
            "8470630": 998,
            "8476468": 824,
            "8475763": 1171,
            "8475855": 822,
            "8475184": 1193,
            "8474613": 1190,
            "8474207": 1214,
            "8475715": 487,
            "8476918": 519,
            "8474151": 1555,
            "8475692": 1224,
            "8473546": 792,
            "8470041": 1074,
            "8475204": 674,
            "8476869": 788,
            "8477402": 1059
        }
    },
    "home_team": "MTL",
    "away_team": "NYR"
}