{
    "game_id": 2017020274,
    "year": 2017,
    "month": 11,
    "day": 15,
    "hour": 3,
    "reg_draw": 0,
    "home_team_id": 26,
    "home_team": "LAK",
    "home_goals": 2,
    "home_coach": "John Stevens",
    "away_team_id": 23,
    "away_team": "VAN",
    "away_goals": 3,
    "away_coach": "Travis Green",
    "players": {
        "home": {
            "8471734": {
                "icetime": 3509,
                "position": "G"
            },
            "8477850": {
                "icetime": 876,
                "position": "D"
            },
            "8474162": {
                "icetime": 1399,
                "position": "D"
            },
            "8480147": {
                "icetime": 997,
                "position": "D"
            },
            "8474563": {
                "icetime": 1516,
                "position": "D"
            },
            "8477960": {
                "icetime": 811,
                "position": "L"
            },
            "8471685": {
                "icetime": 1441,
                "position": "C"
            },
            "8476404": {
                "icetime": 690,
                "position": "L"
            },
            "8480113": {
                "icetime": 1272,
                "position": "C"
            },
            "8476406": {
                "icetime": 833,
                "position": "C"
            },
            "8473453": {
                "icetime": 927,
                "position": "C"
            },
            "8470606": {
                "icetime": 1220,
                "position": "R"
            },
            "8475762": {
                "icetime": 918,
                "position": "D"
            },
            "8469639": {
                "icetime": 540,
                "position": "C"
            },
            "8474166": {
                "icetime": 1504,
                "position": "D"
            },
            "8476020": {
                "icetime": 426,
                "position": "C"
            },
            "8478020": {
                "icetime": 377,
                "position": "C"
            },
            "8476871": {
                "icetime": 978,
                "position": "L"
            },
            "8475726": {
                "icetime": 1068,
                "position": "C"
            }
        },
        "away": {
            "8475195": {
                "icetime": 3596,
                "position": "G"
            },
            "8474584": {
                "icetime": 1134,
                "position": "D"
            },
            "8476884": {
                "icetime": 956,
                "position": "D"
            },
            "8478444": {
                "icetime": 929,
                "position": "R"
            },
            "8473432": {
                "icetime": 990,
                "position": "R"
            },
            "8474091": {
                "icetime": 1199,
                "position": "C"
            },
            "8470626": {
                "icetime": 1070,
                "position": "L"
            },
            "8467875": {
                "icetime": 815,
                "position": "L"
            },
            "8471303": {
                "icetime": 1149,
                "position": "D"
            },
            "8470598": {
                "icetime": 649,
                "position": "L"
            },
            "8477018": {
                "icetime": 1346,
                "position": "D"
            },
            "8467876": {
                "icetime": 805,
                "position": "C"
            },
            "8475790": {
                "icetime": 1399,
                "position": "D"
            },
            "8476466": {
                "icetime": 743,
                "position": "L"
            },
            "8476867": {
                "icetime": 820,
                "position": "C"
            },
            "8477500": {
                "icetime": 970,
                "position": "C"
            },
            "8473415": {
                "icetime": 942,
                "position": "D"
            },
            "8476440": {
                "icetime": 843,
                "position": "C"
            },
            "8474040": {
                "icetime": 646,
                "position": "C"
            }
        }
    }
}