{
    "game_id": 2014021077,
    "year": 2015,
    "month": 3,
    "day": 22,
    "hour": 1,
    "reg_draw": 0,
    "home_team_id": 53,
    "home_team_name": "ARI",
    "home_goals": 1,
    "home_coach": "Dave Tippett",
    "away_team_id": 5,
    "away_team_name": "PIT",
    "away_goals": 3,
    "away_coach": "Mike Johnston",
    "players": {
        "home": {
            "8469608": 3552,
            "8476473": 816,
            "8476356": 1023,
            "8474040": 1394,
            "8474793": 730,
            "8471856": 676,
            "8475186": 1275,
            "8469664": 694,
            "8462038": 1437,
            "8475775": 455,
            "8475414": 591,
            "8475171": 1485,
            "8471231": 1068,
            "8474628": 1314,
            "8471232": 820,
            "8476403": 1266,
            "8476062": 951,
            "8470647": 499,
            "8474638": 1007
        },
        "away": {
            "8470594": 3508,
            "8467452": 1247,
            "8468542": 1503,
            "8473933": 1427,
            "8474096": 907,
            "8470543": 1089,
            "8474091": 865,
            "8471260": 1016,
            "8475761": 594,
            "8471703": 865,
            "8473682": 327,
            "8471476": 1009,
            "8465166": 567,
            "8474013": 1167,
            "8474102": 1022,
            "8470654": 678,
            "8471724": 1869,
            "8471675": 1460
        }
    }
}