{
    "game_id": 2019020537,
    "year": 2019,
    "month": 12,
    "day": 19,
    "hour": 1,
    "reg_draw": 0,
    "home": {
        "team_id": 19,
        "team": "STL",
        "coach": "Craig Berube",
        "GF": 2,
        "GF-5on5": 2,
        "GF-PP": 0,
        "GF-SH": 0,
        "SF": 44,
        "SF-5on5": 32,
        "SF-PP": 12,
        "SF-SH": 0,
        "PIM": 8,
        "PP-O": 5,
        "BLK": 3,
        "TAW": 13,
        "GAW": 10,
        "FO-T": 55,
        "FO-W": 27,
        "HIT": 19
    },
    "away": {
        "team_id": 22,
        "team": "EDM",
        "coach": "Dave Tippett",
        "GF": 1,
        "GF-5on5": 1,
        "GF-PP": 0,
        "GF-SH": 0,
        "SF": 36,
        "SF-5on5": 27,
        "SF-PP": 8,
        "SF-SH": 1,
        "PIM": 10,
        "PP-O": 4,
        "BLK": 13,
        "TAW": 6,
        "GAW": 5,
        "FO-T": 55,
        "FO-W": 28,
        "HIT": 11
    }
}