{
    "game_id": 2019021006,
    "year": 2020,
    "month": 3,
    "day": 1,
    "hour": 1,
    "reg_draw": 1,
    "home": {
        "team_id": 19,
        "team": "STL",
        "coach": "Craig Berube",
        "GF": 3,
        "GF-5on5": 2,
        "GF-PP": 1,
        "GF-SH": 0,
        "SF": 29,
        "SF-5on5": 23,
        "SF-PP": 6,
        "SF-SH": 0,
        "PIM": 0,
        "PP-O": 3,
        "BLK": 10,
        "TAW": 8,
        "GAW": 3,
        "FO-T": 63,
        "FO-W": 36,
        "HIT": 27
    },
    "away": {
        "team_id": 25,
        "team": "DAL",
        "coach": "Rick Bowness",
        "GF": 3,
        "GF-5on5": 3,
        "GF-PP": 0,
        "GF-SH": 0,
        "SF": 31,
        "SF-5on5": 30,
        "SF-PP": 0,
        "SF-SH": 1,
        "PIM": 6,
        "PP-O": 0,
        "BLK": 22,
        "TAW": 9,
        "GAW": 5,
        "FO-T": 63,
        "FO-W": 27,
        "HIT": 27
    }
}